Workbook
Name aporte: APP_INVEST!$D$17:$D$17
Name patrimonio: APP_INVEST!$D$20:$D$20
Name PORCENTAGEM: APP_INVEST!$C$36:$C$36
Name Qtd_Anos: APP_INVEST!$D$18:$D$18
Name Rendimento_Carteira: APP_INVEST!$D$13:$D$13
Name salario: APP_INVEST!$D$12:$D$12
Name sugestao_investimento: APP_INVEST!$D$14:$D$14
Name Taxa_Mensal: APP_INVEST!$D$19:$D$19

Sheet APP_INVEST
B11: Configurações
B12: Salario | D12: 4200
B13: Rendimento carteira | D13: 0.006
B14: Sugestão de investimento (30%) | D14: =D12*0.3 -> 1260
B16: INVESTIMENTO MENSAL
B17: Quanto investir por mês? | D17: 1260
B18: Por Quantos Anos? | D18: 10
B19: Taxa De Rendimento Mensal? | D19: 0.01079
B20: Patrimônio Acumulado? | D20: {=+FV(Taxa_Mensal,Qtd_Anos*12,aporte*-1)} -> 306538.11
B21: Dividendos Mensais? | D21: {=patrimonio*Rendimento_Carteira} -> 1839.2286
B23: CENÁRIOS | D23: Dividendos
A24: 2 | B24: Quanto em 2 Anos | C24: {=FV(Taxa_Mensal,A24*12,aporte*-1)} -> 34306.81 | D24: {=C24*Rendimento_Carteira} -> 205.84086
A25: 5 | B25: Quanto em 5 Anos | C25: {=FV(Taxa_Mensal,A25*12,aporte*-1)} -> 105558.91 | D25: {=C25*Rendimento_Carteira} -> 633.35347
A26: 10 | B26: Quanto em 10 Anos | C26: {=FV(Taxa_Mensal,A26*12,aporte*-1)} -> 306538.11 | D26: {=C26*Rendimento_Carteira} -> 1839.2286
A27: 20 | B27: Quanto em 20 Anos | C27: {=FV(Taxa_Mensal,A27*12,aporte*-1)} -> 1417750 | D27: {=C27*Rendimento_Carteira} -> 8506.4999
A28: 30 | B28: Quanto em 30 Anos | C28: {=FV(Taxa_Mensal,A28*12,aporte*-1)} -> 5445933.8 | D28: {=C28*Rendimento_Carteira} -> 32675.603
B32: PERFIL | C32: AGRESSIVO
B33: VALOR A SER INVESTIDO POR MÊS | D33: 500
B35: TIPO DE FII | C35: Percentual Sugerido | D35: Valores
B36: PAPEL | C36: =VLOOKUP($C$32&"-"&B36,APOIO!A:D,4,FALSE) -> 0.5 | D36: =C36*$D$33 -> 250
B37: TIJOLO | C37: =VLOOKUP($C$32&"-"&B37,APOIO!A:D,4,FALSE) -> 0.1 | D37: =C37*$D$33 -> 50
B38: HIBRIDO | C38: =VLOOKUP($C$32&"-"&B38,APOIO!A:D,4,FALSE) -> 0.05 | D38: =C38*$D$33 -> 25
B39: FOFs | C39: =VLOOKUP($C$32&"-"&B39,APOIO!A:D,4,FALSE) -> 0.05 | D39: =C39*$D$33 -> 25
B40: DESENVOLVIMENTO | C40: =VLOOKUP($C$32&"-"&B40,APOIO!A:D,4,FALSE) -> 0.2 | D40: =C40*$D$33 -> 100
B41: HOTELARIAS | C41: =VLOOKUP($C$32&"-"&B41,APOIO!A:D,4,FALSE) -> 0.1 | D41: =C41*$D$33 -> 50
D42: =SUM(D36:D41) -> 500

Sheet APOIO
I5: %
A6: Chave | B6: PERFIL | C6: TIPO DE FII | D6: % | H6: MODERADO-TIJOLO | I6: =VLOOKUP(H6,A:D,4,FALSE) -> 0.4
A7: =B7&"-"&C7 -> CONSERVADOR-PAPEL | B7: CONSERVADOR | C7: PAPEL | D7: 0.3
A8: =B8&"-"&C8 -> CONSERVADOR-TIJOLO | B8: CONSERVADOR | C8: TIJOLO | D8: 0.5
A9: =B9&"-"&C9 -> CONSERVADOR-HIBRIDO | B9: CONSERVADOR | C9: HIBRIDO | D9: 0.1
A10: =B10&"-"&C10 -> CONSERVADOR-FOFs | B10: CONSERVADOR | C10: FOFs | D10: 0.1
A11: =B11&"-"&C11 -> CONSERVADOR-DESENVOLVIMENTO | B11: CONSERVADOR | C11: DESENVOLVIMENTO | D11: 0
A12: =B12&"-"&C12 -> CONSERVADOR-HOTELARIAS | B12: CONSERVADOR | C12: HOTELARIAS | D12: 0
A13: =B13&"-"&C13 -> MODERADO-PAPEL | B13: MODERADO | C13: PAPEL | D13: 0.32
A14: =B14&"-"&C14 -> MODERADO-TIJOLO | B14: MODERADO | C14: TIJOLO | D14: 0.4
A15: =B15&"-"&C15 -> MODERADO-HIBRIDO | B15: MODERADO | C15: HIBRIDO | D15: 0.08
A16: =B16&"-"&C16 -> MODERADO-FOFs | B16: MODERADO | C16: FOFs | D16: 0.1
A17: =B17&"-"&C17 -> MODERADO-DESENVOLVIMENTO | B17: MODERADO | C17: DESENVOLVIMENTO | D17: 0.1
A18: =B18&"-"&C18 -> MODERADO-HOTELARIAS | B18: MODERADO | C18: HOTELARIAS | D18: 0.1
... A24: =B24&"-"&C24 -> AGRESSIVO-HOTELARIAS | B24: AGRESSIVO | C24: HOTELARIAS | D24: 0.1
